<?xml version="1.0" encoding="UTF-8"?>
<UnityGameFramework>
  <BuildReport>
    <Summary>
      <ProductName>unityclient</ProductName>
      <CompanyName>DefaultCompany</CompanyName>
      <GameIdentifier>com.DefaultCompany.unityclient</GameIdentifier>
      <GameFrameworkVersion>2021.05.31</GameFrameworkVersion>
      <UnityVersion>2021.3.15f1c1</UnityVersion>
      <ApplicableGameVersion>0.1</ApplicableGameVersion>
      <InternalResourceVersion>0</InternalResourceVersion>
      <Platforms>Windows</Platforms>
      <AssetBundleCompression>LZ4</AssetBundleCompression>
      <CompressionHelperTypeName>UnityGameFramework.Runtime.DefaultCompressionHelper</CompressionHelperTypeName>
      <AdditionalCompressionSelected>False</AdditionalCompressionSelected>
      <ForceRebuildAssetBundleSelected>False</ForceRebuildAssetBundleSelected>
      <BuildEventHandlerTypeName>
      </BuildEventHandlerTypeName>
      <OutputDirectory>D:/Games/repo/AbyssX/dojo-unity/unityclient/ABOutput</OutputDirectory>
      <BuildAssetBundleOptions>DeterministicAssetBundle, ChunkBasedCompression</BuildAssetBundleOptions>
    </Summary>
    <Resources Count="0" />
  </BuildReport>
</UnityGameFramework>